inelsmqttbus/__init__.py
inelsmqttbus/const.py
inelsmqttbus/device.py
inelsmqttbus/discovery.py
inels_mqtt_bus-0.0.6.dist-info/LICENSE
inels_mqtt_bus-0.0.6.dist-info/METADATA
inels_mqtt_bus-0.0.6.dist-info/WHEEL
inels_mqtt_bus-0.0.6.dist-info/top_level.txt
inels_mqtt_bus-0.0.6.dist-info/RECORD
