Metadata-Version: 2.1
Name: inels-mqtt-bus
Version: 0.0.6
Summary: Python library for iNels mqtt protocol, bus version
Home-page: https://github.com/zed4805/inels-mqtt-bus
Author: Elko EP s.r.o.
Author-email: zed4805@gmail.com
License: MIT
Keywords: iNels,Elko EP,Home assistant integration
Classifier: License :: OSI Approved :: MIT License
Classifier: Programming Language :: Python :: 3
Classifier: Programming Language :: Python :: 3.9
License-File: LICENSE
